climate_finance/README.md
climate_finance/__init__.py
climate_finance/common/__init__.py
climate_finance/common/analysis_tools.py
climate_finance/common/match_projects_to_crs.py
climate_finance/common/schema.py
climate_finance/config.py
climate_finance/core/__init__.py
climate_finance/core/data.py
climate_finance/core/deflators.py
climate_finance/core/dtypes.py
climate_finance/core/enums.py
climate_finance/core/loaders.py
climate_finance/core/oecd_classification.csv
climate_finance/core/tools.py
climate_finance/core/validation.py
climate_finance/methodologies/__init__.py
climate_finance/methodologies/bilateral/__init__.py
climate_finance/methodologies/bilateral/tools.py
climate_finance/methodologies/multilateral/__init__.py
climate_finance/methodologies/multilateral/crs_tools.py
climate_finance/methodologies/multilateral/oecd_multilateral/__init__.py
climate_finance/methodologies/multilateral/oecd_multilateral/get_oecd_imputations.py
climate_finance/methodologies/multilateral/one_multilateral/__init__.py
climate_finance/methodologies/multilateral/one_multilateral/shares.py
climate_finance/methodologies/multilateral/tools.py
climate_finance/methodologies/spending/__init__.py
climate_finance/methodologies/spending/crdf.py
climate_finance/methodologies/spending/crdf_crs.py
climate_finance/methodologies/spending/crs.py
climate_finance/methodologies/spending/tools.py
climate_finance/oecd/__init__.py
climate_finance/oecd/cleaning_tools/__init__.py
climate_finance/oecd/cleaning_tools/crs_channel_mapping.csv
climate_finance/oecd/cleaning_tools/names.py
climate_finance/oecd/cleaning_tools/provider_agency_names.feather
climate_finance/oecd/cleaning_tools/provider_names.feather
climate_finance/oecd/cleaning_tools/recipient_names.feather
climate_finance/oecd/cleaning_tools/settings.py
climate_finance/oecd/cleaning_tools/tools.py
climate_finance/oecd/crdf/__init__.py
climate_finance/oecd/crdf/provider_perspective.py
climate_finance/oecd/crdf/recipient_perspective.py
climate_finance-1.2.2.dist-info/WHEEL
climate_finance-1.2.2.dist-info/METADATA
climate_finance-1.2.2.dist-info/RECORD
