Metadata-Version: 2.4
Name: climate-finance
Version: 1.2.2
Summary: Climate Finance data
Keywords: climate,finance,data,oecd,unfccc
Author: Jorge Rivera
Author-email: Jorge Rivera <jorge.rivera@one.org>
License-Expression: MIT
Classifier: Development Status :: 4 - Beta
Classifier: Intended Audience :: Science/Research
Classifier: License :: OSI Approved :: MIT License
Classifier: Operating System :: OS Independent
Classifier: Programming Language :: Python :: 3
Classifier: Programming Language :: Python :: 3.11
Classifier: Programming Language :: Python :: 3.12
Classifier: Programming Language :: Python :: 3.13
Classifier: Topic :: Scientific/Engineering
Requires-Dist: bblocks>=1.4.3,<2
Requires-Dist: oda-data>=2.3.1
Requires-Dist: openpyxl>=3.1.5
Requires-Dist: pandas>=2.3.2
Requires-Dist: requests>=2.32.5
Requires-Dist: selenium>=4.35.0
Requires-Dist: thefuzz[speedup]>=0.22.1
Requires-Dist: webdriver-manager>=4.0.2
Requires-Python: >=3.11
Project-URL: Homepage, https://github.com/ONEcampaign/climate-finance-package
Project-URL: Issues, https://github.com/ONEcampaign/climate-finance-package/issues
Project-URL: Repository, https://github.com/ONEcampaign/climate-finance-package
